chat_user/__init__.py
chat_user/example.py
chat_user/frontend/build/asset-manifest.json
chat_user/frontend/build/bootstrap.min.css
chat_user/frontend/build/index.html
chat_user/frontend/build/static/js/main.1caf1f65.js
chat_user/frontend/build/static/js/main.1caf1f65.js.LICENSE.txt
chat_user/frontend/build/static/js/main.1caf1f65.js.map
chat_user/frontend/build/static/js/main.74f7f1f9.js
chat_user/frontend/build/static/js/main.74f7f1f9.js.LICENSE.txt
chat_user/frontend/build/static/js/main.74f7f1f9.js.map
chat_user-1.0.0.dist-info/LICENSE
chat_user-1.0.0.dist-info/METADATA
chat_user-1.0.0.dist-info/WHEEL
chat_user-1.0.0.dist-info/top_level.txt
chat_user-1.0.0.dist-info/RECORD
